sanityze/__init__.py
sanityze/cleanser.py
sanityze/spotters.py
sanityze-1.0.2.dist-info/METADATA
sanityze-1.0.2.dist-info/WHEEL
sanityze-1.0.2.dist-info/LICENSE
sanityze-1.0.2.dist-info/RECORD
