Metadata-Version: 2.1
Name: sanityze
Version: 1.0.2
Summary: Python package to help datascientists remove or redact Personal Identifiable Information (PII) 
License: MIT
Author: Caesar Wong, Jonah Hamilton and Tony Zoght
Requires-Python: >=3.9,<4.0
Classifier: License :: OSI Approved :: MIT License
Classifier: Programming Language :: Python :: 3
Classifier: Programming Language :: Python :: 3.9
Classifier: Programming Language :: Python :: 3.10
Classifier: Programming Language :: Python :: 3.11
Requires-Dist: pandas (>=1.5.2,<2.0.0)
